ewtpy/__init__.py
ewtpy/ewtpy.py
ewtpy-0.1.dist-info/LICENSE.txt
ewtpy-0.1.dist-info/METADATA
ewtpy-0.1.dist-info/WHEEL
ewtpy-0.1.dist-info/top_level.txt
ewtpy-0.1.dist-info/RECORD
