Metadata-Version: 2.1
Name: ewtpy
Version: 0.1
Summary: Empirical Wavelet Transofrm (EWT) algorithm
Home-page: http://github.com/vrcarva/ewtpy
Author: Vinicius Rezende Carvalho
Author-email: vrcarva@ufmg.br
License: UNKNOWN
Keywords: EWT,empirical,wavelet
Platform: UNKNOWN
Classifier: Development Status :: 3 - Alpha
Classifier: Intended Audience :: Science/Research
Classifier: Topic :: Scientific/Engineering :: Mathematics
Classifier: License :: OSI Approved :: MIT License
Classifier: Programming Language :: Python :: 3
Requires-Dist: numpy
Requires-Dist: scipy
